genoa/Genoa.py
genoa/__init__.py
genoa-0.3.5.dist-info/METADATA
genoa-0.3.5.dist-info/WHEEL
genoa-0.3.5.dist-info/top_level.txt
genoa-0.3.5.dist-info/RECORD
